corejam/__init__.py
corejam/__main__.py
corejam/argparse.py
corejam/exceptions.py
corejam/io.py
corejam/logging.py
corejam-0.0.2.data/data/LICENSE
tests/__init__.py
tests/test_io.py
corejam-0.0.2.dist-info/LICENSE
corejam-0.0.2.dist-info/METADATA
corejam-0.0.2.dist-info/WHEEL
corejam-0.0.2.dist-info/entry_points.txt
corejam-0.0.2.dist-info/top_level.txt
corejam-0.0.2.dist-info/RECORD
