Metadata-Version: 2.1
Name: corejam
Version: 0.0.2
Summary: corejam
Home-page: https://github.com/aaronmussig/corejam
Author: Aaron Mussig
Author-email: aaronmussig@gmail.com
License: GPL3
Project-URL: Bug Tracker, https://github.com/aaronmussig/corejam/issues
Project-URL: Documentation, https://github.com/aaronmussig/corejam
Project-URL: Source Code, https://github.com/aaronmussig/corejam
Keywords: corejam
Platform: UNKNOWN
Classifier: Development Status :: 4 - Beta
Classifier: Intended Audience :: Science/Research
Classifier: License :: OSI Approved :: GNU General Public License v3 (GPLv3)
Classifier: Natural Language :: English
Classifier: Operating System :: OS Independent
Classifier: Programming Language :: Python :: 3.6
Classifier: Programming Language :: Python :: 3.7
Classifier: Programming Language :: Python :: 3.8
Classifier: Topic :: Scientific/Engineering :: Bio-Informatics
Requires-Python: >=3.6
